easyw2v/__init__.py
easyw2v/__main__.py
easyw2v-0.0.0.dist-info/LICENSE.txt
easyw2v-0.0.0.dist-info/METADATA
easyw2v-0.0.0.dist-info/WHEEL
easyw2v-0.0.0.dist-info/top_level.txt
easyw2v-0.0.0.dist-info/RECORD
