Metadata-Version: 2.1
Name: easyw2v
Version: 0.0.0
Summary: Easy generation of semantic vectors from a corpus in Terminal
Home-page: https://github.com/msaito8623/easyw2v
Author: Motoki Saito
Author-email: motoki.saito@uni-tuebingen.de
License: MIT
Platform: UNKNOWN
Classifier: Development Status :: 3 - Alpha
Classifier: Environment :: Console
Classifier: Intended Audience :: Science/Research
Classifier: License :: OSI Approved :: MIT License
Classifier: Operating System :: POSIX :: Linux
Classifier: Programming Language :: Python
Classifier: Programming Language :: Python :: 3.7
Classifier: Programming Language :: Python :: 3.8
Classifier: Programming Language :: Python :: 3 :: Only
Classifier: Topic :: Scientific/Engineering
Requires-Dist: gensim
Requires-Dist: pathlib
Requires-Dist: numpy
Requires-Dist: pyper
Requires-Dist: xarray
Requires-Dist: argparse
Provides-Extra: docs
Requires-Dist: sphinx ; extra == 'docs'
Requires-Dist: sphinx-rtd-theme ; extra == 'docs'
Provides-Extra: tests
Requires-Dist: pytest ; extra == 'tests'
